bripinfo/.files/.gitkeep
bripinfo/__init__.py
bripinfo/__main__.py
bripinfo/commands.py
bripinfo/core.py
bripinfo/registro_br.py
bripinfo/settings.py
bripinfo-2.0.1.dist-info/LICENSE
bripinfo-2.0.1.dist-info/METADATA
bripinfo-2.0.1.dist-info/WHEEL
bripinfo-2.0.1.dist-info/RECORD
