Metadata-Version: 2.1
Name: bripinfo
Version: 2.0.1
Summary: Uma maneira fácil de obter dados relativos a um IP associado ao Registro.br.
Home-page: https://github.com/rogeriopaulos/BRIpinfo
License: MIT
Author: Rogerio Paulo
Author-email: rogeriopaulos@gmail.com
Requires-Python: >=3.10,<4.0
Classifier: License :: OSI Approved :: MIT License
Classifier: Programming Language :: Python :: 3
Classifier: Programming Language :: Python :: 3.10
Classifier: Programming Language :: Python :: 3.11
Classifier: Programming Language :: Python :: 3.12
Requires-Dist: click (==8.1.7)
Requires-Dist: requests (==2.32.3)
Requires-Dist: urllib3 (==2.2.1)
Project-URL: Documentation, https://github.com/rogeriopaulos/BRIpinfo
Project-URL: Repository, https://github.com/rogeriopaulos/BRIpinfo
